{
    "photos": [
        {   "ID":1,
            "Heure": "10 06 2015 14:41:30",
            "Lien": "static/photos/09-06-2015_14:41:27.jpg",
            "Nom": "09-06-2015_14:41:27.jpg"
        },
        {   "ID":2,   
            "Lien": "static/photos/09-06-2015_16:14:37.jpg",
            "Heure": "09 06 2015 16:14:40",
            "Nom": "09-06-2015_16:14:37.jpg"
        },
        {   "ID":3,
            "Heure": "09 06 2015 16:14:55",
            "Lien": "static/photos/09-06-2015_16:14:52.jpg",
            "Nom": "09-06-2015_16:14:52.jpg"
        },
        {   "ID":4,
            "Lien": "static/photos/09-06-2015_16:14:56.jpg",
            "Heure": "09 06 2015 16:14:59",
            "Nom": "09-06-2015_16:14:56.jpg"
        },
        {   "ID":5,
            "Heure": "09 06 2015 16:15:07",
            "Lien": "static/photos/09-06-2015_16:15:04.jpg",
            "Nom": "09-06-2015_16:15:04.jpg"
        },
        {   "ID":6,
            "Lien": "static/photos/09-06-2015_16:15:17.jpg",
            "Heure": "09 06 2015 16:15:20",
            "Nom": "09-06-2015_16:15:17.jpg"
        },
        {   "ID":7,
            "Heure": "09 06 2015 16:15:24",
            "Lien": "static/photos/09-06-2015_16:15:21.jpg",
            "Nom": "09-06-2015_16:15:21.jpg"
        },
        {   "ID":8,
            "Lien": "static/photos/09-06-2015_17:53:35.jpg",
            "Heure": "09 06 2015 17:53:38",
            "Nom": "09-06-2015_17:53:35.jpg"
        },
        {   "ID":9,
            "Heure": "09 06 2015 17:53:42",
            "Lien": "static/photos/09-06-2015_17:53:39.jpg",
            "Nom": "09-06-2015_17:53:39.jpg"
        },
        {   "ID":10,
            "Lien": "static/photos/09-06-2015_17:53:43.jpg",
            "Heure": "09 06 2015 17:53:45",
            "Nom": "09-06-2015_17:53:43.jpg"
        },
        {   "ID":11,
            "Heure": "09 06 2015 17:53:49",
            "Lien": "static/photos/09-06-2015_17:53:46.jpg",
            "Nom": "09-06-2015_17:53:46.jpg"
        }
    ]
}